llreval/__init__.py
llreval/bayes_error_rate.py
llreval/cllr.py
llreval/pav_rocch.py
llreval/plotting.py
llreval/quick_eval.py
llreval/utils.py
llreval-0.0.3.dist-info/LICENSE
llreval-0.0.3.dist-info/METADATA
llreval-0.0.3.dist-info/WHEEL
llreval-0.0.3.dist-info/top_level.txt
llreval-0.0.3.dist-info/RECORD
