Metadata-Version: 2.1
Name: llreval
Version: 0.0.3
Summary: Python package for the log-likelihood-ratio
Author-email: Niko Brummer <niko.brummer@gmail.com>, "David A. van Leeuwen" <david.vanleeuwen@gmail.com>
License: MIT License
Project-URL: Homepage, https://github.com/davidavdav/llreval
Project-URL: Bug Tracker, https://github.com/davidavdav/llreval/issues
Classifier: Programming Language :: Python :: 3
Classifier: License :: OSI Approved :: MIT License
Classifier: Operating System :: OS Independent
Requires-Python: >=3.7
License-File: LICENSE
Requires-Dist: matplotlib
Requires-Dist: numpy
Requires-Dist: scipy
Requires-Dist: scikit-learn
